httpx_oauth/__init__.py
httpx_oauth/branding.py
httpx_oauth/exceptions.py
httpx_oauth/oauth2.py
httpx_oauth/py.typed
httpx_oauth/clients/__init__.py
httpx_oauth/clients/discord.py
httpx_oauth/clients/facebook.py
httpx_oauth/clients/franceconnect.py
httpx_oauth/clients/github.py
httpx_oauth/clients/google.py
httpx_oauth/clients/kakao.py
httpx_oauth/clients/linkedin.py
httpx_oauth/clients/microsoft.py
httpx_oauth/clients/naver.py
httpx_oauth/clients/okta.py
httpx_oauth/clients/openid.py
httpx_oauth/clients/reddit.py
httpx_oauth/clients/shopify.py
httpx_oauth/integrations/__init__.py
httpx_oauth/integrations/fastapi.py
httpx_oauth-0.16.0.dist-info/METADATA
httpx_oauth-0.16.0.dist-info/WHEEL
httpx_oauth-0.16.0.dist-info/licenses/LICENSE
httpx_oauth-0.16.0.dist-info/RECORD
