Metadata-Version: 2.3
Name: httpx-oauth
Version: 0.16.0
Summary: Async OAuth client using HTTPX
Project-URL: Documentation, https://frankie567.github.io/httpx-oauth/
Project-URL: Source, https://github.com/frankie567/httpx-oauth
Author-email: François Voron <fvoron@gmail.com>
Classifier: Development Status :: 5 - Production/Stable
Classifier: Framework :: AsyncIO
Classifier: Intended Audience :: Developers
Classifier: License :: OSI Approved :: MIT License
Classifier: Programming Language :: Python :: 3 :: Only
Classifier: Programming Language :: Python :: 3.9
Classifier: Programming Language :: Python :: 3.10
Classifier: Programming Language :: Python :: 3.11
Classifier: Programming Language :: Python :: 3.12
Classifier: Programming Language :: Python :: 3.13
Requires-Python: >=3.9
Requires-Dist: httpx<0.28,>=0.18
